akshat_invo/__init__.py
akshat_invo/text_splitter.py
akshat_invo/agents/__init__.py
akshat_invo/agents/agent_toolkits/__init__.py
akshat_invo/agents/agent_toolkits/csv/__init__.py
akshat_invo/agents/agent_toolkits/csv/base.py
akshat_invo/agents/agent_toolkits/pandas/__init__.py
akshat_invo/agents/agent_toolkits/pandas/base.py
akshat_invo/agents/agent_toolkits/pandas/prompt.py
akshat_invo/agents/agent_toolkits/python/__init__.py
akshat_invo/agents/agent_toolkits/python/base.py
akshat_invo/agents/agent_toolkits/python/prompt.py
akshat_invo/agents/agent_toolkits/spark/__init__.py
akshat_invo/agents/agent_toolkits/spark/base.py
akshat_invo/agents/agent_toolkits/spark/prompt.py
akshat_invo/agents/agent_toolkits/xorbits/__init__.py
akshat_invo/agents/agent_toolkits/xorbits/base.py
akshat_invo/agents/agent_toolkits/xorbits/prompt.py
akshat_invo/autonomous_agents/__init__.py
akshat_invo/autonomous_agents/autogpt/__init__.py
akshat_invo/autonomous_agents/autogpt/agent.py
akshat_invo/autonomous_agents/autogpt/memory.py
akshat_invo/autonomous_agents/autogpt/output_parser.py
akshat_invo/autonomous_agents/autogpt/prompt.py
akshat_invo/autonomous_agents/autogpt/prompt_generator.py
akshat_invo/autonomous_agents/baby_agi/__init__.py
akshat_invo/autonomous_agents/baby_agi/baby_agi.py
akshat_invo/autonomous_agents/baby_agi/task_creation.py
akshat_invo/autonomous_agents/baby_agi/task_execution.py
akshat_invo/autonomous_agents/baby_agi/task_prioritization.py
akshat_invo/autonomous_agents/hugginggpt/__init__.py
akshat_invo/autonomous_agents/hugginggpt/hugginggpt.py
akshat_invo/autonomous_agents/hugginggpt/repsonse_generator.py
akshat_invo/autonomous_agents/hugginggpt/task_executor.py
akshat_invo/autonomous_agents/hugginggpt/task_planner.py
akshat_invo/chat_models/__init__.py
akshat_invo/chat_models/llm_wrapper.py
akshat_invo/comprehend_moderation/__init__.py
akshat_invo/comprehend_moderation/amazon_comprehend_moderation.py
akshat_invo/comprehend_moderation/base_moderation.py
akasht_invo-0.1.dist-info/METADATA
akasht_invo-0.1.dist-info/WHEEL
akasht_invo-0.1.dist-info/top_level.txt
akasht_invo-0.1.dist-info/RECORD
